urbancode/__init__.py
urbancode/network/__init__.py
urbancode/network/centrality.py
urbancode/network/connectivity.py
urbancode/network/core.py
urbancode/network/utils.py
urbancode/network/visualization.py
urbancode/svi/__init__.py
urbancode/svi/feature.py
urbancode/svi/perception.py
urbancode-0.2.1.dist-info/licenses/LICENSE
urbancode-0.2.1.dist-info/METADATA
urbancode-0.2.1.dist-info/WHEEL
urbancode-0.2.1.dist-info/top_level.txt
urbancode-0.2.1.dist-info/RECORD
