Metadata-Version: 2.4
Name: urbancode
Version: 0.2.1
Summary: A package for universal urban analysis
Home-page: https://github.com/Sijie-Yang/urbancode
Author: Sijie Yang
Author-email: sijiey@u.nus.edu
Project-URL: Bug Tracker, https://github.com/Sijie-Yang/urbancode/issues
Project-URL: Changelog, https://github.com/Sijie-Yang/urbancode/blob/main/CHANGELOG.md
Classifier: Development Status :: 3 - Alpha
Classifier: Intended Audience :: Developers
Classifier: License :: OSI Approved :: MIT License
Classifier: Operating System :: OS Independent
Classifier: Programming Language :: Python :: 3
Classifier: Programming Language :: Python :: 3.8
Classifier: Programming Language :: Python :: 3.9
Classifier: Programming Language :: Python :: 3.10
Classifier: Programming Language :: Python :: 3.11
Requires-Python: >=3.8
License-File: LICENSE
Requires-Dist: networkx>=2.5
Requires-Dist: osmnx>=1.1.1
Requires-Dist: momepy>=0.5.3
Requires-Dist: geopandas>=0.9.0
Requires-Dist: matplotlib>=3.3.4
Requires-Dist: torch>=2.0.0
Requires-Dist: torchvision>=0.15.0
Requires-Dist: pillow>=9.0.0
Requires-Dist: pandas>=1.2.0
Requires-Dist: scikit-learn>=0.24.0
Requires-Dist: tqdm>=4.60.0
Requires-Dist: tensorboard>=2.5.0
Requires-Dist: opencv-python>=4.5.0
Requires-Dist: scipy>=1.7.0
Requires-Dist: transformers>=4.30.0
Requires-Dist: accelerate>=0.20.0
Requires-Dist: safetensors>=0.3.1
Requires-Dist: urllib3>=2.0.0
Requires-Dist: requests>=2.0.0
Provides-Extra: dev
Requires-Dist: pytest>=6.0; extra == "dev"
Requires-Dist: pytest-cov>=2.0; extra == "dev"
Requires-Dist: flake8>=3.9.0; extra == "dev"
Requires-Dist: black>=21.0; extra == "dev"
Requires-Dist: isort>=5.0; extra == "dev"
Requires-Dist: jupyter>=1.0.0; extra == "dev"
Requires-Dist: ipywidgets>=8.0.0; extra == "dev"
Dynamic: author
Dynamic: author-email
Dynamic: classifier
Dynamic: description
Dynamic: description-content-type
Dynamic: home-page
Dynamic: license-file
Dynamic: project-url
Dynamic: provides-extra
Dynamic: requires-dist
Dynamic: requires-python
Dynamic: summary
